faqap/__init__.py
faqap/fw.py
faqap/misc.py
faqap/permutation.py
faqap/torch.py
faqap/test/__init__.py
faqap/test/benchmark.py
faqap/test/permutation.py
faqap/test/test.py
faqap/test/test_torch.py
faqap-0.3.0.dist-info/METADATA
faqap-0.3.0.dist-info/WHEEL
faqap-0.3.0.dist-info/top_level.txt
faqap-0.3.0.dist-info/RECORD
