Metadata-Version: 2.1
Name: faqap
Version: 0.3.0
Summary: Algorithm for approximately solving quadratic assignment problems.
Home-page: https://github.com/sogartar/faqap
Author: sogartar
Author-email: sogartary@yahoo.com
License: Unlicense
Platform: UNKNOWN
Classifier: Development Status :: 3 - Alpha
Classifier: License :: OSI Approved :: The Unlicense (Unlicense)
Classifier: Intended Audience :: Developers
Classifier: Operating System :: OS Independent
Classifier: Programming Language :: Python :: 3
Requires-Python: >=3.5
Requires-Dist: numpy (>=1.10)
Requires-Dist: scipy (>=1.4)
Provides-Extra: torch
Requires-Dist: torch ; extra == 'torch'
